datumaro/__init__.py
datumaro/__main__.py
datumaro/_capi.cpython-39-x86_64-linux-gnu.so
datumaro/errors.py
datumaro/ops.py
datumaro/rust_api.cpython-39-x86_64-linux-gnu.so
datumaro/version.py
datumaro/capi/pybind.cpp
datumaro/cli/__init__.py
datumaro/cli/__main__.py
datumaro/cli/commands/__init__.py
datumaro/cli/commands/compare.py
datumaro/cli/commands/convert.py
datumaro/cli/commands/detect_format.py
datumaro/cli/commands/download.py
datumaro/cli/commands/filter.py
datumaro/cli/commands/info.py
datumaro/cli/commands/merge.py
datumaro/cli/commands/patch.py
datumaro/cli/commands/stats.py
datumaro/cli/commands/transform.py
datumaro/cli/commands/validate.py
datumaro/cli/commands/downloaders/__init__.py
datumaro/cli/commands/downloaders/downloader.py
datumaro/cli/commands/downloaders/kaggle.py
datumaro/cli/commands/downloaders/kaggle_formats.json
datumaro/cli/commands/downloaders/tfds.py
datumaro/cli/contexts/__init__.py
datumaro/cli/contexts/util.py
datumaro/cli/helpers/__init__.py
datumaro/cli/helpers/format.py
datumaro/cli/util/__init__.py
datumaro/cli/util/compare.py
datumaro/cli/util/dataset_utils.py
datumaro/cli/util/errors.py
datumaro/components/__init__.py
datumaro/components/annotation.py
datumaro/components/cli_plugin.py
datumaro/components/comparator.py
datumaro/components/config.py
datumaro/components/config_model.py
datumaro/components/dataset.py
datumaro/components/dataset_base.py
datumaro/components/dataset_item_storage.py
datumaro/components/dataset_storage.py
datumaro/components/environment.py
datumaro/components/errors.py
datumaro/components/exporter.py
datumaro/components/extractor_tfds.py
datumaro/components/filter.py
datumaro/components/format_detection.py
datumaro/components/generator.py
datumaro/components/importer.py
datumaro/components/lazy_plugin.py
datumaro/components/media.py
datumaro/components/operations.py
datumaro/components/progress_reporting.py
datumaro/components/registry.py
datumaro-1.12.0.dist-info/METADATA
datumaro-1.12.0.dist-info/WHEEL
datumaro-1.12.0.dist-info/entry_points.txt
datumaro-1.12.0.dist-info/top_level.txt
datumaro-1.12.0.dist-info/RECORD
datumaro-1.12.0.dist-info/licenses/LICENSE
datumaro-1.12.0.dist-info/licenses/NOTICE
