Metadata-Version: 2.4
Name: datumaro
Version: 1.12.0
Summary: Dataset Management Framework (Datumaro)
Home-page: https://github.com/open-edge-platform/datumaro
Author: Intel
Author-email: emily.chun@intel.com
License: MIT
Classifier: Programming Language :: Python :: 3
Classifier: Operating System :: OS Independent
Requires-Python: >=3.9
License-File: LICENSE
License-File: NOTICE
Requires-Dist: attrs>=21.3.0
Requires-Dist: defusedxml>=0.7.0
Requires-Dist: imagesize>=1.4.1
Requires-Dist: lxml<7,>=5.2.0
Requires-Dist: numpy<2.2.0,>=1.23.4
Requires-Dist: orjson>=3.10.0
Requires-Dist: Pillow>=10.3.0
Requires-Dist: ruamel.yaml>=0.17.0
Requires-Dist: shapely>=1.7
Requires-Dist: typing_extensions>=3.7.4.3
Requires-Dist: tqdm>=4.67.1
Requires-Dist: pycocotools>=2.0.4
Requires-Dist: PyYAML==6.0.2
Requires-Dist: pandas>=1.4.0
Requires-Dist: pyarrow
Requires-Dist: json-stream
Requires-Dist: opencv-python
Provides-Extra: tf
Requires-Dist: tensorflow; extra == "tf"
Provides-Extra: tfds
Requires-Dist: tensorflow-datasets<4.9.3; extra == "tfds"
Requires-Dist: absl-py>=0.12.0; extra == "tfds"
Provides-Extra: torch
Requires-Dist: torch; extra == "torch"
Requires-Dist: torchvision; extra == "torch"
Provides-Extra: kaggle
Requires-Dist: kaggle; extra == "kaggle"
Provides-Extra: scipy
Requires-Dist: scipy; extra == "scipy"
Provides-Extra: nlp
Requires-Dist: nltk; extra == "nlp"
Requires-Dist: tokenizers; extra == "nlp"
Requires-Dist: portalocker; extra == "nlp"
Provides-Extra: tabulate
Requires-Dist: tabulate; extra == "tabulate"
Provides-Extra: cli
Requires-Dist: tensorboardX!=2.3,>=1.8; extra == "cli"
Requires-Dist: tabulate; extra == "cli"
Requires-Dist: scipy; extra == "cli"
Requires-Dist: matplotlib>=3.3.1; extra == "cli"
Provides-Extra: visualizer
Requires-Dist: matplotlib>=3.3.1; extra == "visualizer"
Provides-Extra: h5py
Requires-Dist: h5py>=2.10.0; extra == "h5py"
Provides-Extra: nibabel
Requires-Dist: nibabel>=3.2.1; extra == "nibabel"
Provides-Extra: protobuf
Requires-Dist: protobuf; extra == "protobuf"
Provides-Extra: experimental
Requires-Dist: polars<2.0.0,>=1.31.0; extra == "experimental"
Dynamic: author
Dynamic: author-email
Dynamic: classifier
Dynamic: description
Dynamic: description-content-type
Dynamic: home-page
Dynamic: license
Dynamic: license-file
Dynamic: provides-extra
Dynamic: requires-dist
Dynamic: requires-python
Dynamic: summary
